odoo9_addon_crm_rma_stock_location-9.0.1.0.0.99.dev6-py2.7-nspkg.pth
odoo9_addon_crm_rma_stock_location-9.0.1.0.0.99.dev6.dist-info/METADATA
odoo9_addon_crm_rma_stock_location-9.0.1.0.0.99.dev6.dist-info/RECORD
odoo9_addon_crm_rma_stock_location-9.0.1.0.0.99.dev6.dist-info/WHEEL
odoo9_addon_crm_rma_stock_location-9.0.1.0.0.99.dev6.dist-info/namespace_packages.txt
odoo9_addon_crm_rma_stock_location-9.0.1.0.0.99.dev6.dist-info/top_level.txt
odoo_addons/crm_rma_stock_location/README.rst
odoo_addons/crm_rma_stock_location/__init__.py
odoo_addons/crm_rma_stock_location/__openerp__.py
odoo_addons/crm_rma_stock_location/init_hooks.py
odoo_addons/crm_rma_stock_location/demo/stock_inventory.xml
odoo_addons/crm_rma_stock_location/demo/stock_location.xml
odoo_addons/crm_rma_stock_location/i18n/crm_rma_stock_location.pot
odoo_addons/crm_rma_stock_location/i18n/de.po
odoo_addons/crm_rma_stock_location/i18n/es.po
odoo_addons/crm_rma_stock_location/i18n/es_MX.po
odoo_addons/crm_rma_stock_location/i18n/es_PA.po
odoo_addons/crm_rma_stock_location/i18n/es_VE.po
odoo_addons/crm_rma_stock_location/i18n/fr.po
odoo_addons/crm_rma_stock_location/i18n/pt_BR.po
odoo_addons/crm_rma_stock_location/i18n/ro.po
odoo_addons/crm_rma_stock_location/i18n/sl.po
odoo_addons/crm_rma_stock_location/models/__init__.py
odoo_addons/crm_rma_stock_location/models/product_product.py
odoo_addons/crm_rma_stock_location/models/product_template.py
odoo_addons/crm_rma_stock_location/models/stock_warehouse.py
odoo_addons/crm_rma_stock_location/static/description/icon.png
odoo_addons/crm_rma_stock_location/tests/__init__.py
odoo_addons/crm_rma_stock_location/tests/test_crm_rma_stock_location.py
odoo_addons/crm_rma_stock_location/tests/test_make_picking_from_picking.py
odoo_addons/crm_rma_stock_location/tests/test_rma_stock.py
odoo_addons/crm_rma_stock_location/views/crm_claim.xml
odoo_addons/crm_rma_stock_location/views/product_product.xml
odoo_addons/crm_rma_stock_location/views/product_template.xml
odoo_addons/crm_rma_stock_location/views/stock_picking.xml
odoo_addons/crm_rma_stock_location/views/stock_warehouse.xml
odoo_addons/crm_rma_stock_location/wizards/__init__.py
odoo_addons/crm_rma_stock_location/wizards/claim_make_picking.py
odoo_addons/crm_rma_stock_location/wizards/claim_make_picking_from_picking.py
