Metadata-Version: 2.1
Name: odoo9-addon-crm-rma-stock-location
Version: 9.0.1.0.0.99.dev6
Summary: RMA Stock Location
Home-page: http://www.camptocamp.com,http://www.vauxoo.com
Author: Akretion,Vauxoo,Camptocamp,Odoo Community Association (OCA)
Author-email: support@odoo-community.org
License: AGPL-3
Platform: UNKNOWN
Classifier: Programming Language :: Python
Classifier: Framework :: Odoo
Classifier: License :: OSI Approved :: GNU Affero General Public License v3
Requires-Python: ~=2.7
Requires-Dist: odoo9-addon-crm-claim-rma
Requires-Dist: odoo9-addon-crm-rma-location
Requires-Dist: odoo (<9.1a,>=9.0a)
